Workbook

Sheet Employees
A1: Employee ID | B1: Employee Name | C1: DOJ | D1: CTC | E1: Calendar Days | F1: Paid Days | G1: LOP day's | I1: Basic | J1: HRA | K1: Special Allowance | L1: Other Allowance | M1: Gross Income | N1: Employee PF (12%) | O1: Employee ESI (0.75%) | P1: Professional Tax | Q1: Arrears | R1: Reimbursements | S1: Bonus/Incentive | T1: Gross Earnings | U1: TDS | V1: LOP Deduction | W1: Other Deductions | X1: Employer PF (12%) | Y1: Employer ESI (3.25%) | Z1: Gratuity (4.81%) | AA1: Total Deductions | AB1: Correction | AC1: Net Salary Payable
A2: AGS26006 | B2: Abhijeet Vijaysingh Pardeshi | C2: 46062 | D2: 70833 | E2: 31 | F2: 31 | G2: 0 | I2: =(+D2*50%)/E2*F2 -> 35416.5 | J2: =(I2*50%) -> 17708.25 | K2: =(1600/E2)*F2 -> 1600 | L2: =(M2-I2-J2-K2) -> 12604.716 | M2: =((D2-X2)/E2*F2)-Z2 -> 67329.466 | N2: =IF($I2*0.12>1800,1800,$I2*0.12) -> 1800 | O2: =IF(M2<=21000,M2*0.75%,0) -> 0 | P2: 200 | Q2: 0 | R2: 0 | S2: 0 | T2: =M2+Q2+R2+S2 -> 67329.466 | U2: 0 | V2: 0 | W2: 0 | X2: =IF($I2*0.12>1800,1800,$I2*0.12) -> 1800 | Y2: =IF(M2<=21000,M2*3.25%,0) -> 0 | Z2: =I2*4.81% -> 1703.5336 | AA2: =N2+O2+P2+V2+W2+U2+X2+Y2+Z2 -> 5503.5336 | AB2: 1 | AC2: =M2-AA2+AB2+N2+Z2 -> 65330.466
A3: AGS26038 | B3: Ainala Saiesha | C3: 46086 | D3: 100000 | E3: 31 | F3: 27 | G3: 0 | I3: =(+D3*49.99999%)/E3*F3 -> 43548.378 | J3: =(I3*50%) -> 21774.189 | K3: =(1600/E3)*F3 -> 1393.5484 | L3: =(M3-I3-J3-K3) -> 16718.239 | M3: =(D3-X3)/E3*F3-Z3 -> 83434.355 | N3: =IF($I3*0.12>1800,1800,$I3*0.12) -> 1800 | O3: =IF(M3<=21000,M3*0.75%,0) -> 0 | P3: 200 | Q3: 0 | R3: 0 | S3: 0 | T3: =M3+Q3+R3+S3 -> 83434.355 | U3: 0 | V3: 0 | W3: 0 | X3: =IF($I3*0.12>1800,1800,$I3*0.12) -> 1800 | Y3: =IF(M3<=21000,M3*3.25%,0) -> 0 | Z3: =I3*4.81% -> 2094.677 | AA3: =N3+O3+P3+V3+W3+U3+X3+Y3+Z3 -> 5894.677 | AC3: =M3-AA3+AB3+N3+Z3 -> 81434.355
C7: Total | D7: =SUM(D2:D6) -> 170833 | I7: =SUM(I2:I6) -> 78964.878 | J7: =SUM(J2:J6) -> 39482.439 | K7: =SUM(K2:K6) -> 2993.5484 | L7: =SUM(L2:L6) -> 29322.956 | M7: =SUM(M2:M6) -> 150763.82 | N7: =SUM(N2:N6) -> 3600 | O7: =SUM(O2:O6) -> 0 | P7: =SUM(P2:P6) -> 400 | ... AA7: =SUM(AA2:AA6) -> 11398.211 | AC7: =SUM(AC2:AC6) -> 146764.82

Sheet Consultant
A1: Employee ID | B1: Employee Name | C1: DOJ | D1: CTC | E1: Actuals | F1: TDS | G1: PT | H1: Payable | I1: LOP
A2: AGS26004 | B2: Ande Sharath Chandra | C2: 46055 | D2: 80000 | E2: =D2/31*31 -> 80000 | F2: 0 | G2: 200 | H2: =E2-G2 -> 79800
A3: AGS26005 | B3: Tanakala Janardhan | C3: 46055 | D3: 70000 | E3: =D3/31*31 -> 70000 | F3: 0 | G3: 200 | H3: =E3-G3 -> 69800
A4: AGS26020 | B4: Gurindapalli Krishna Chaitanya | C4: 46066 | D4: 60000 | E4: =D4/31*31 -> 60000 | F4: 0 | G4: 200 | H4: =E4-G4 -> 59800
A5: AGS26024 | B5: Priya Darshini Pola | C5: 46072 | D5: 80000 | E5: 80000 | F5: 0 | G5: 200 | H5: =E5-G5 -> 79800
A6: AGS26039 | B6: Esther Deva Priya | C6: 46092 | D6: 20000 | E6: =D6/31*21 -> 13548.387 | F6: 0 | G6: 200 | H6: =E6-G6 -> 13348.387
G7: Total | H7: =SUM(H2:H6) -> 302548.39

Sheet Tech Employees
A1: Employee ID | B1: Employee Name | C1: DOJ | D1: CTC | E1: Calendar Days | F1: Paid Days | G1: LOP day's | I1: Abasic | J1: Basic | K1: AHRA | L1: HRA | M1: ASA | N1: Spec Allo | O1: AOA | P1: Other Allowance | Q1: Gross Income | R1: Employee PF (12%) | S1: Employee ESI (0.75%) | T1: Professional Tax | U1: Arrears | V1: Reimbursements | W1: Bonus/Incentive | X1: Gross Earnings | Y1: TDS | Z1: LOP Deduction | AA1: Other Deductions | AB1: Employer PF (12%) | AC1: Employer ESI (3.25%) | AD1: Gratuity (4.81%) | AE1: Total Deductions | AF1: Net Salary Payable
A2: AGS26011 | B2: Siddula Hemasai | C2: 46083 | D2: 45000 | E2: 30 | F2: 30 | G2: 0 | I2: =(+D2*49.99999%)/E2*E2 -> 22499.995 | J2: =(+D2*49.99999%)/E2*F2 -> 22499.995 | K2: =(I2*50%) -> 11249.998 | L2: =(J2*50%) -> 11249.998 | M2: 1600 | N2: =(1600/E2)*F2 -> 1600 | O2: =D2-I2-K2-M2-AB2-AD2 -> 6767.757 | P2: =(Q2-J2-L2-N2) -> 6767.757 | Q2: =(D2-AB2)/E2*F2-AD2 -> 42117.75 | R2: =IF($J2*0.12>1800,1800,$J2*0.12) -> 1800 | S2: =IF(Q2<=21000,Q2*0.75%,0) -> 0 | T2: 200 | U2: 0 | V2: 0 | W2: 0 | X2: =Q2+U2+V2+W2 -> 42117.75 | Y2: 0 | Z2: 0 | AA2: 0 | AB2: =IF($J2*0.12>1800,1800,$J2*0.12) -> 1800 | AC2: 0 | AD2: =J2*4.81% -> 1082.2498 | AE2: =R2+S2+T2+Z2+AA2+Y2+AB2+AC2+AD2 -> 4882.2498 | AF2: =Q2-AE2+AD2+AB2 -> 40117.75
A3: AGS26018 | B3: Settybathini Sathish | C3: 46083 | D3: 45000 | E3: 30 | F3: 30 | G3: 0 | I3: =(+D3*49.99999%)/E3*E3 -> 22499.995 | J3: =(+D3*49.99999%)/E3*F3 -> 22499.995 | K3: =(I3*50%) -> 11249.998 | L3: =(J3*50%) -> 11249.998 | M3: 1600 | N3: =(1600/E3)*F3 -> 1600 | O3: =D3-I3-K3-M3-AB3-AD3 -> 6767.757 | P3: =(Q3-J3-L3-N3) -> 6767.757 | Q3: =(D3-AB3)/E3*F3-AD3 -> 42117.75 | R3: =IF($J3*0.12>1800,1800,$J3*0.12) -> 1800 | S3: =IF(Q3<=21000,Q3*0.75%,0) -> 0 | T3: 200 | U3: 0 | V3: 0 | W3: 0 | X3: =Q3+U3+V3+W3 -> 42117.75 | Y3: 0 | Z3: 0 | AA3: 0 | AB3: =IF($J3*0.12>1800,1800,$J3*0.12) -> 1800 | AC3: 0 | AD3: =J3*4.81% -> 1082.2498 | AE3: =R3+S3+T3+Z3+AA3+Y3+AB3+AC3+AD3 -> 4882.2498 | AF3: =Q3-AE3+AD3+AB3 -> 40117.75
A4: AGS26010 | B4: Vemula Varshith | C4: 46083 | D4: 60000 | E4: 30 | F4: 30 | G4: 0 | I4: =(+D4*49.99999%)/E4*E4 -> 29999.994 | J4: =(+D4*49.99999%)/E4*F4 -> 29999.994 | K4: =(I4*50%) -> 14999.997 | L4: =(J4*50%) -> 14999.997 | M4: 1600 | N4: =(1600/E4)*F4 -> 1600 | O4: =D4-I4-K4-M4-AB4-AD4 -> 10157.009 | P4: =(Q4-J4-L4-N4) -> 10157.009 | Q4: =(D4-AB4)/E4*F4-AD4 -> 56757 | R4: =IF($J4*0.12>1800,1800,$J4*0.12) -> 1800 | S4: =IF(Q4<=21000,Q4*0.75%,0) -> 0 | T4: 200 | U4: 0 | V4: 0 | W4: 0 | X4: =Q4+U4+V4+W4 -> 56757 | Y4: 0 | Z4: 0 | AA4: 0 | AB4: =IF($J4*0.12>1800,1800,$J4*0.12) -> 1800 | AC4: 0 | AD4: =J4*4.81% -> 1442.9997 | AE4: =R4+S4+T4+Z4+AA4+Y4+AB4+AC4+AD4 -> 5242.9997 | AF4: =Q4-AE4+AD4+AB4 -> 54757
A5: AGS26019 | B5: Nelapatla Srinivas | C5: 46083 | D5: 23000 | E5: 30 | F5: 30 | G5: 0 | I5: =(+D5*49.99999%)/E5*E5 -> 11499.998 | J5: =(+D5*49.99999%)/E5*F5 -> 11499.998 | K5: =(I5*50%) -> 5749.9988 | L5: =(J5*50%) -> 5749.9988 | M5: 1600 | N5: =(1600/E5)*F5 -> 1600 | O5: =D5-I5-K5-M5-AB5-AD5 -> 2216.8538 | P5: =(Q5-J5-L5-N5) -> 2216.8538 | Q5: =(D5-AB5)/E5*F5-AD5 -> 21066.85 | R5: =IF($J5*0.12>1800,1800,$J5*0.12) -> 1379.9997 | S5: =IF(Q5<=21000,Q5*0.75%,0) -> 0 | T5: 150 | U5: 0 | V5: 0 | W5: 0 | X5: =Q5+U5+V5+W5 -> 21066.85 | Y5: 0 | Z5: 0 | AA5: 0 | AB5: =IF($J5*0.12>1800,1800,$J5*0.12) -> 1379.9997 | AC5: 0 | AD5: =J5*4.81% -> 553.14989 | AE5: =R5+S5+T5+Z5+AA5+Y5+AB5+AC5+AD5 -> 3463.1493 | AF5: =Q5-AE5+AD5+AB5 -> 19536.851
A6: AGS26014 | B6: Vulli Pavan | C6: 46083 | D6: 50000 | E6: 30 | F6: 30 | G6: 0 | I6: =(+D6*49.99999%)/E6*E6 -> 24999.995 | J6: =(+D6*49.99999%)/E6*F6 -> 24999.995 | K6: =(I6*50%) -> 12499.997 | L6: =(J6*50%) -> 12499.997 | M6: 1600 | N6: =(1600/E6)*F6 -> 1600 | O6: =D6-I6-K6-M6-AB6-AD6 -> 7897.5077 | P6: =(Q6-J6-L6-N6) -> 7897.5077 | Q6: =(D6-AB6)/E6*F6-AD6 -> 46997.5 | R6: =IF($J6*0.12>1800,1800,$J6*0.12) -> 1800 | S6: =IF(Q6<=21000,Q6*0.75%,0) -> 0 | T6: 200 | U6: 0 | V6: 0 | W6: 0 | X6: =Q6+U6+V6+W6 -> 46997.5 | Y6: 0 | Z6: 0 | AA6: 0 | AB6: =IF($J6*0.12>1800,1800,$J6*0.12) -> 1800 | AC6: 0 | AD6: =J6*4.81% -> 1202.4998 | AE6: =R6+S6+T6+Z6+AA6+Y6+AB6+AC6+AD6 -> 5002.4998 | AF6: =Q6-AE6+AD6+AB6 -> 44997.5
A7: AGS26017 | B7: Vavilla Saikumar | C7: 46083 | D7: 45000 | E7: 30 | F7: 30 | G7: 0 | I7: =(+D7*49.99999%)/E7*E7 -> 22499.995 | J7: =(+D7*49.99999%)/E7*F7 -> 22499.995 | K7: =(I7*50%) -> 11249.998 | L7: =(J7*50%) -> 11249.998 | M7: 1600 | N7: =(1600/E7)*F7 -> 1600 | O7: =D7-I7-K7-M7-AB7-AD7 -> 6767.757 | P7: =(Q7-J7-L7-N7) -> 6767.757 | Q7: =(D7-AB7)/E7*F7-AD7 -> 42117.75 | R7: =IF($J7*0.12>1800,1800,$J7*0.12) -> 1800 | S7: =IF(Q7<=21000,Q7*0.75%,0) -> 0 | T7: 200 | U7: 0 | V7: 0 | W7: 0 | X7: =Q7+U7+V7+W7 -> 42117.75 | Y7: 0 | Z7: 0 | AA7: 0 | AB7: =IF($J7*0.12>1800,1800,$J7*0.12) -> 1800 | AC7: 0 | AD7: =J7*4.81% -> 1082.2498 | AE7: =R7+S7+T7+Z7+AA7+Y7+AB7+AC7+AD7 -> 4882.2498 | AF7: =Q7-AE7+AD7+AB7 -> 40117.75
A8: AGS26016 | B8: Manisha Ashroba Virkar | C8: 46083 | D8: 45000 | E8: 30 | F8: 30 | G8: 0 | I8: =(+D8*49.99999%)/E8*E8 -> 22499.995 | J8: =(+D8*49.99999%)/E8*F8 -> 22499.995 | K8: =(I8*50%) -> 11249.998 | L8: =(J8*50%) -> 11249.998 | M8: 1600 | N8: =(1600/E8)*F8 -> 1600 | O8: =D8-I8-K8-M8-AB8-AD8 -> 6767.757 | P8: =(Q8-J8-L8-N8) -> 6767.757 | Q8: =(D8-AB8)/E8*F8-AD8 -> 42117.75 | R8: =IF($J8*0.12>1800,1800,$J8*0.12) -> 1800 | S8: =IF(Q8<=21000,Q8*0.75%,0) -> 0 | T8: 200 | U8: 0 | V8: 0 | W8: 0 | X8: =Q8+U8+V8+W8 -> 42117.75 | Y8: 0 | Z8: 0 | AA8: 0 | AB8: =IF($J8*0.12>1800,1800,$J8*0.12) -> 1800 | AC8: 0 | AD8: =J8*4.81% -> 1082.2498 | AE8: =R8+S8+T8+Z8+AA8+Y8+AB8+AC8+AD8 -> 4882.2498 | AF8: =Q8-AE8+AD8+AB8 -> 40117.75
A9: AGS26015 | B9: Karne Narsimha Reddy | C9: 46083 | D9: 45000 | E9: 30 | F9: 30 | G9: 0 | I9: =(+D9*49.99999%)/E9*E9 -> 22499.995 | J9: =(+D9*49.99999%)/E9*F9 -> 22499.995 | K9: =(I9*50%) -> 11249.998 | L9: =(J9*50%) -> 11249.998 | M9: 1600 | N9: =(1600/E9)*F9 -> 1600 | O9: =D9-I9-K9-M9-AB9-AD9 -> 6767.757 | P9: =(Q9-J9-L9-N9) -> 6767.757 | Q9: =(D9-AB9)/E9*F9-AD9 -> 42117.75 | R9: =IF($J9*0.12>1800,1800,$J9*0.12) -> 1800 | S9: =IF(Q9<=21000,Q9*0.75%,0) -> 0 | T9: 200 | U9: 0 | V9: 0 | W9: 0 | X9: =Q9+U9+V9+W9 -> 42117.75 | Y9: 0 | Z9: 0 | AA9: 0 | AB9: =IF($J9*0.12>1800,1800,$J9*0.12) -> 1800 | AC9: 0 | AD9: =J9*4.81% -> 1082.2498 | AE9: =R9+S9+T9+Z9+AA9+Y9+AB9+AC9+AD9 -> 4882.2498 | AF9: =Q9-AE9+AD9+AB9 -> 40117.75
A10: AGS26013 | B10: Kalepu Vijay | C10: 46083 | D10: 45000 | E10: 30 | F10: 30 | G10: 0 | I10: =(+D10*49.99999%)/E10*E10 -> 22499.995 | J10: =(+D10*49.99999%)/E10*F10 -> 22499.995 | K10: =(I10*50%) -> 11249.998 | L10: =(J10*50%) -> 11249.998 | M10: 1600 | N10: =(1600/E10)*F10 -> 1600 | O10: =D10-I10-K10-M10-AB10-AD10 -> 6767.757 | P10: =(Q10-J10-L10-N10) -> 6767.757 | Q10: =(D10-AB10)/E10*F10-AD10 -> 42117.75 | R10: =IF($J10*0.12>1800,1800,$J10*0.12) -> 1800 | S10: =IF(Q10<=21000,Q10*0.75%,0) -> 0 | T10: 200 | U10: 0 | V10: 0 | W10: 0 | X10: =Q10+U10+V10+W10 -> 42117.75 | Y10: 0 | Z10: 0 | AA10: 0 | AB10: =IF($J10*0.12>1800,1800,$J10*0.12) -> 1800 | AC10: 0 | AD10: =J10*4.81% -> 1082.2498 | AE10: =R10+S10+T10+Z10+AA10+Y10+AB10+AC10+AD10 -> 4882.2498 | AF10: =Q10-AE10+AD10+AB10 -> 40117.75
A11: AGS26021 | B11: Kontham Sushma | C11: 46083 | D11: 50000 | E11: 30 | F11: 30 | G11: 0 | I11: =(+D11*49.99999%)/E11*E11 -> 24999.995 | J11: =(+D11*49.99999%)/E11*F11 -> 24999.995 | K11: =(I11*50%) -> 12499.997 | L11: =(J11*50%) -> 12499.997 | M11: 1600 | N11: =(1600/E11)*F11 -> 1600 | O11: =D11-I11-K11-M11-AB11-AD11 -> 7897.5077 | P11: =(Q11-J11-L11-N11) -> 7897.5077 | Q11: =(D11-AB11)/E11*F11-AD11 -> 46997.5 | R11: =IF($J11*0.12>1800,1800,$J11*0.12) -> 1800 | S11: =IF(Q11<=21000,Q11*0.75%,0) -> 0 | T11: 200 | U11: 0 | V11: 0 | W11: 0 | X11: =Q11+U11+V11+W11 -> 46997.5 | Y11: 0 | Z11: 0 | AA11: 0 | AB11: =IF($J11*0.12>1800,1800,$J11*0.12) -> 1800 | AC11: 0 | AD11: =J11*4.81% -> 1202.4998 | AE11: =R11+S11+T11+Z11+AA11+Y11+AB11+AC11+AD11 -> 5002.4998 | AF11: =Q11-AE11+AD11+AB11 -> 44997.5
A12: AGS26022 | B12: Akkma Sai Teja | C12: 46083 | D12: 50000 | E12: 30 | F12: 30 | G12: 0 | I12: =(+D12*49.99999%)/E12*E12 -> 24999.995 | J12: =(+D12*49.99999%)/E12*F12 -> 24999.995 | K12: =(I12*50%) -> 12499.997 | L12: =(J12*50%) -> 12499.997 | M12: 1600 | N12: =(1600/E12)*F12 -> 1600 | O12: =D12-I12-K12-M12-AB12-AD12 -> 7897.5077 | P12: =(Q12-J12-L12-N12) -> 7897.5077 | Q12: =(D12-AB12)/E12*F12-AD12 -> 46997.5 | R12: =IF($J12*0.12>1800,1800,$J12*0.12) -> 1800 | S12: =IF(Q12<=21000,Q12*0.75%,0) -> 0 | T12: 200 | U12: 0 | V12: 0 | W12: 0 | X12: =Q12+U12+V12+W12 -> 46997.5 | Y12: 0 | Z12: 0 | AA12: 0 | AB12: =IF($J12*0.12>1800,1800,$J12*0.12) -> 1800 | AC12: 0 | AD12: =J12*4.81% -> 1202.4998 | AE12: =R12+S12+T12+Z12+AA12+Y12+AB12+AC12+AD12 -> 5002.4998 | AF12: =Q12-AE12+AD12+AB12 -> 44997.5
A13: AGS26023 | B13: Bobbarala Varshini | C13: 46083 | D13: 60000 | E13: 30 | F13: 30 | G13: 0 | I13: =(+D13*49.99999%)/E13*E13 -> 29999.994 | J13: =(+D13*49.99999%)/E13*F13 -> 29999.994 | K13: =(I13*50%) -> 14999.997 | L13: =(J13*50%) -> 14999.997 | M13: 1600 | N13: =(1600/E13)*F13 -> 1600 | O13: =D13-I13-K13-M13-AB13-AD13 -> 10157.009 | P13: =(Q13-J13-L13-N13) -> 10157.009 | Q13: =(D13-AB13)/E13*F13-AD13 -> 56757 | R13: =IF($J13*0.12>1800,1800,$J13*0.12) -> 1800 | S13: =IF(Q13<=21000,Q13*0.75%,0) -> 0 | T13: 200 | U13: 0 | V13: 0 | W13: 0 | X13: =Q13+U13+V13+W13 -> 56757 | Y13: 0 | Z13: 0 | AA13: 0 | AB13: =IF($J13*0.12>1800,1800,$J13*0.12) -> 1800 | AC13: 0 | AD13: =J13*4.81% -> 1442.9997 | AE13: =R13+S13+T13+Z13+AA13+Y13+AB13+AC13+AD13 -> 5242.9997 | AF13: =Q13-AE13+AD13+AB13 -> 54757
... A21: AGS26035 | B21: Varakantham Surender Reddy | C21: 46083 | D21: 60000 | E21: 30 | F21: 30 | G21: 0 | I21: =(+D21*49.99999%)/E21*E21 -> 29999.994 | J21: =(+D21*49.99999%)/E21*F21 -> 29999.994 | K21: =(I21*50%) -> 14999.997 | L21: =(J21*50%) -> 14999.997 | M21: 1600 | N21: =(1600/E21)*F21 -> 1600 | O21: =D21-I21-K21-M21-AB21-AD21 -> 10157.009 | P21: =(Q21-J21-L21-N21) -> 10157.009 | Q21: =(D21-AB21)/E21*F21-AD21 -> 56757 | R21: =IF($J21*0.12>1800,1800,$J21*0.12) -> 1800 | S21: =IF(Q21<=21000,Q21*0.75%,0) -> 0 | T21: 200 | U21: 0 | V21: 0 | W21: 0 | X21: =Q21+U21+V21+W21 -> 56757 | Y21: 0 | Z21: 0 | AA21: 0 | AB21: =IF($J21*0.12>1800,1800,$J21*0.12) -> 1800 | AC21: 0 | AD21: =J21*4.81% -> 1442.9997 | AE21: =R21+S21+T21+Z21+AA21+Y21+AB21+AC21+AD21 -> 5242.9997 | AF21: =Q21-AE21+AD21+AB21 -> 54757
A22: AGS26041 | B22: Sudhagani Sai Charan | C22: 46113
A23: AGS26043 | B23: Chebrolu Yashaswini | C23: 46113
A24: AGS26044 | B24: Pulikonda Naveen | C24: 46113
A25: AGS26045 | B25: Chebrolu Monika | C25: 46113
A26: AGS26047 | B26: Upadhyayula Naga Lakshmi Deepthi | C26: 46113
A27: AGS26048 | B27: Rapolu Rekha | C27: 46113
A28: AGS26049 | B28: Ragiru Nikhitha | C28: 46113
A29: AGS26051 | B29: Mundlamuri Mrudula | C29: 46113
A30: AGS26055 | B30: Cholleti Sai Kumar | C30: 46113
A31: AGS26053 | B31: Palavelli Praveen Reddy | C31: 46113
A32: AGS26054 | B32: Yaramothu Himaja | C32: 46113
A33: AGS26031 | B33: Y Raghavendar | C33: 46113
... A39: AGS26059 | B39: Thallada Venkatasagar | C39: 46113
C41: Total | D41: =SUM(D2:D21) -> 886000 | I41: =SUM(I2:I21) -> 442999.91 | J41: =SUM(J2:J21) -> 442999.91 | K41: =SUM(K2:K21) -> 221499.96 | L41: =SUM(L2:L21) -> 221499.96 | M41: =SUM(M2:M21) -> 32000 | N41: =SUM(N2:N21) -> 32000 | O41: =SUM(O2:O21) -> 133931.84 | P41: =SUM(P2:P21) -> 133931.84 | ... X41: =SUM(X2:X21) -> 830431.7 | AB41: =SUM(AB2:AB21) -> 34259.999 | AD41: =SUM(AD2:AD21) -> 21308.296 | AE41: =SUM(AE2:AE21) -> 93781.339 | AF41: =SUM(AF2:AF21) -> 792218.66

Sheet Payment
A1: Employee ID | B1: Employee Name | C1: DOJ | D1: Net Salary Payable | E1: Bank Account Number | F1: IFSC code | G1: Bank Name | H1: Remarks
A2: AGS26006 | B2: Abhijeet Vijaysingh Pardeshi | C2: 46062 | D2: =Employees!AC2 -> 65330.466 | E2: 41280100007853 | F2: BARB0WALUJX | G2: BANK OF BARODA
A3: AGS26038 | B3: Ainala Saiesha | C3: 46086 | D3: =Employees!AC3 -> 81434.355 | E3: 50100868298601 | F3: HDFC0003665 | G3: HDFC Bank
A4: AGS26004 | B4: Ande Sharath Chandra | C4: 46054 | D4: =VLOOKUP(A4,Consultant!A2:H6,8,0) -> 79800 | E4: 50100677371816 | F4: HDFC0001042 | G4: HDFC Bank
A5: AGS26005 | B5: Tanakala Janardhan | C5: 46054 | D5: =VLOOKUP(A5,Consultant!A2:H6,8,0) -> 69800 | E5: 154710100018477 | F5: UBIN0815471 | G5: Union Bank
A6: AGS26020 | B6: Gurindapalli Krishna Chaitanya | C6: 46066 | D6: =VLOOKUP(A6,Consultant!A2:H6,8,0) -> 59800 | E6: 020201545829 | F6: ICIC0000202 | G6: ICICI Bank
A7: AGS26024 | B7: Priya Darshini Pola | C7: 46072 | D7: =VLOOKUP(A7,Consultant!A2:H6,8,0) -> 79800 | E7: 770301501355 | F7: ICIC0007703 | G7: ICICI Bank
A8: AGS26039 | B8: Esther Deva Priya | C8: 46092 | D8: =VLOOKUP(A8,Consultant!A2:H6,8,0) -> 13348.387 | E8: 50100743220366 | F8: HDFC0000545 | G8: HDFC Bank
A9: AGS26011 | B9: Siddula Hemasai | C9: 46083 | D9: =VLOOKUP(A9,'Tech Employees'!A2:AF21,32,0) -> 40117.75 | E9: 3327101004003 | F9: CNRB0003327 | G9: Canara Bank
A10: AGS26018 | B10: Settybathini Sathish | C10: 46083 | D10: =VLOOKUP(A10,'Tech Employees'!A3:AF41,32,0) -> 40117.75 | E10: 50100595290241 | F10: HDFC0000075 | G10: HDFC Bank
A11: AGS26010 | B11: Vemula Varshith | C11: 46083 | D11: =VLOOKUP(A11,'Tech Employees'!A4:AF42,32,0) -> 54757 | E11: 62428832885 | F11: SBIN0020959 | G11: State Bank of India
A12: AGS26019 | B12: Nelapatla Srinivas | C12: 46083 | D12: =VLOOKUP(A12,'Tech Employees'!A5:AF43,32,0) -> 19536.851 | E12: 62442668281 | F12: SBIN0020176 | G12: State Bank of India
A13: AGS26014 | B13: Vulli Pavan | C13: 46083 | D13: =VLOOKUP(A13,'Tech Employees'!A6:AF44,32,0) -> 44997.5 | E13: 77770116800885 | F13: FDRL0007777 | G13: Federal Bank
A14: AGS26017 | B14: Vavilla Saikumar | C14: 46083 | D14: =VLOOKUP(A14,'Tech Employees'!A7:AF45,32,0) -> 40117.75 | E14: 41085488775 | F14: SBIN0016293 | G14: State Bank of India
A15: AGS26016 | B15: Manisha Ashroba Virkar | C15: 46083 | D15: =VLOOKUP(A15,'Tech Employees'!A8:AF46,32,0) -> 40117.75 | E15: 62297418711 | F15: SBIN0003801 | G15: State Bank of India
A16: AGS26015 | B16: Karne Narsimha Reddy | C16: 46083 | D16: =VLOOKUP(A16,'Tech Employees'!A9:AF47,32,0) -> 40117.75 | E16: 1446178000009714 | F16: KVBL0001446 | G16: Karur Vysya Bank
A17: AGS26013 | B17: Kalepu Vijay | C17: 46083 | D17: =VLOOKUP(A17,'Tech Employees'!A10:AF48,32,0) -> 40117.75 | E17: 159502740717 | F17: INDB0000329 | G17: INDUSIND BANK
A18: AGS26021 | B18: Kontham Sushma | C18: 46083 | D18: =VLOOKUP(A18,'Tech Employees'!A11:AF49,32,0) -> 44997.5 | E18: 39569845546 | F18: SBIN0008024 | G18: State Bank of India
A19: AGS26022 | B19: Akkma Sai Teja | C19: 46083 | D19: =VLOOKUP(A19,'Tech Employees'!A12:AF50,32,0) -> 44997.5 | E19: 50100565431077 | F19: HDFC0005175 | G19: HDFC Bank
A20: AGS26023 | B20: Bobbarala Varshini | C20: 46083 | D20: =VLOOKUP(A20,'Tech Employees'!A13:AF51,32,0) -> 54757 | E20: 41202390653 | F20: SBIN0000910 | G20: State Bank of India
A21: AGS26026 | B21: Surampudi Roop Sai | C21: 46083 | D21: =VLOOKUP(A21,'Tech Employees'!A14:AF52,32,0) -> 54757 | E21: 615728726 | F21: IDIB000P121 | G21: Indian Bank
A22: AGS26028 | B22: Mohammed Abdul Moid | C22: 46083 | D22: =VLOOKUP(A22,'Tech Employees'!A15:AF53,32,0) -> 12586.206 | E22: 9147600708 | F22: KKBK0007474 | G22: Kotak
A23: AGS26029 | B23: Mula Sai Preetham Goud | C23: 46083 | D23: =VLOOKUP(A23,'Tech Employees'!A16:AF54,32,0) -> 30358.25 | E23: 7445588605 | F23: KKBK0007462 | G23: Kotak
A24: AGS26030 | B24: Sruthin Kumar Basa | C24: 46083 | D24: =VLOOKUP(A24,'Tech Employees'!A17:AF55,32,0) -> 30358.25 | E24: 4495101004331 | F24: CNRB0004495 | G24: Canara Bank
A25: AGS26032 | B25: Vempadapu Uday Sai Tarun | C25: 46083 | D25: =VLOOKUP(A25,'Tech Employees'!A18:AF56,32,0) -> 19536.851 | E25: 37182972098 | F25: SBIN0008054 | G25: State Bank of India
A26: AGS26033 | B26: Kethavath Sai Raj | C26: 46083 | D26: =VLOOKUP(A26,'Tech Employees'!A19:AF57,32,0) -> 30358.25 | E26: 39971511897 | F26: SBIN0021227 | G26: State Bank of India
A27: AGS26034 | B27: Sripada Shivakumar | C27: 46083 | D27: =VLOOKUP(A27,'Tech Employees'!A20:AF58,32,0) -> 54757 | E27: 41536691505 | F27: SBIN0008807 | G27: State Bank of India
A28: AGS26035 | B28: Varakantham Surender Reddy | C28: 46083 | D28: =VLOOKUP(A28,'Tech Employees'!A21:AF59,32,0) -> 54757 | E28: 50100141200194 | F28: HDFC0004480 | G28: HDFC Bank
B30: Total | D30: =SUM(D2:D28) -> 1241531.9

Sheet Trainers
A1: S.No | B1: Name | C1: No of Hours | D1: Cost per Hour | E1: Total Cost | F1: Bank Account Number | G1: IFSC code | H1: Banking Name | I1: Bank | J1: Skill
A2: 1 | B2: Sridhar | E2: 230000 | F2: 32862142889 | G2: SBIN0011121 | H2: ERGAMREDDY SARADHA | I2: SBI | J2: CTO
A3: 2 | B3: Sreekanth (Arjun) | C3: 1 | D3: 1200 | E3: =C3*D3 -> 1200 | F3: 004001579702 | G3: ICIC0001806 | H3: Sreekanth Koraboina | I3: ICICI Bank | J3: QA
A4: 3 | B4: Ravi | C4: 1 | D4: 1200 | E4: =C4*D4 -> 1200 | F4: 653101004326 | G4: ICIC0000053 | H4: G Ravi Teja | I4: ICICI Bank | J4: DevOps
A5: 4 | B5: Venkatesh Salla | C5: 1 | D5: 1000 | E5: =C5*D5 -> 1000 | F5: 23310559930 | G5: SCBL0036090 | H5: Salla Venkatesh | I5: Standard Chartered Bank | J5: AI
A6: 5 | B6: Madhuri | C6: 1 | D6: 1000 | E6: =C6*D6 -> 1000 | F6: 814649188 | G6: IDIB000C026 | H6: K GOPINADH | I6: INDIAN BANK | J6: PowerBI
A7: 6 | B7: Chetna | C7: 1 | D7: 1000 | E7: =C7*D7 -> 1000
A8: 7 | B8: Akshay | C8: 1 | D8: 800 | E8: =C8*D8 -> 800
E10: =SUM(E2:E9) -> 236200

Sheet Rental Amount
A1: S.No | B1: Month | C1: Receiver | D1: Account Number | E1: IFSC Code | F1: Bank | G1: Amount | H1: GST | I1: Total
A2: 1 | B2: April | C2: ODCET Consultancy Services Pvt Ltd | D2: 50200062999445 | E2: HDFC0000364 | F2: HDFC | G2: 160000 | H2: =G2*0.18 -> 28800 | I2: =G2+H2 -> 188800
