Workbook

Sheet Employees
A1: Employee ID | B1: Employee Name | C1: DOJ | D1: CTC | E1: Calendar Days | F1: Paid Days | G1: LOP day's | I1: Basic | J1: HRA | K1: Special Allowance | L1: Other Allowance | M1: Gross Income | N1: Employee PF (12%) | O1: Employee ESI (0.75%) | P1: Professional Tax | Q1: Arrears | R1: Reimbursements | S1: Bonus/Incentive | T1: Gross Earnings | U1: TDS | V1: LOP Deduction | W1: Other Deductions | X1: Employer PF (12%) | Y1: Employer ESI (3.25%) | Z1: Gratuity (4.81%) | AA1: Total Deductions | AB1: Net Salary Payable
A2: AGS26007 | B2: Mandela Sai Sandeep | C2: 46062 | D2: 116667 | E2: 28 | F2: 16 | G2: 4 | I2: =(+D2*49.99999%)/E2*F2 -> 33333.422 | J2: =(I2*50%) -> 16666.711 | K2: =(1600/E2)*F2 -> 914.28571 | L2: =(M2-I2-J2-K2) -> 13120.53 | M2: =(D2-X2)/E2*F2-Z2 -> 64034.948 | N2: =IF($I2*0.12>1800,1800,$I2*0.12) -> 1800 | O2: =IF(M2<=21000,M2*0.75%,0) -> 0 | P2: 200 | Q2: 0 | R2: 0 | S2: 0 | T2: =M2+Q2+R2+S2 -> 64034.948 | U2: 0 | V2: 0 | W2: 0 | X2: =IF($I2*0.12>1800,1800,$I2*0.12) -> 1800 | Y2: =IF(M2<=21000,M2*3.25%,0) -> 0 | Z2: =I2*4.81% -> 1603.3376 | AA2: =N2+O2+P2+V2+W2+U2+X2+Y2+Z2 -> 5403.3376 | AB2: =M2-AA2 -> 58631.611
A3: AGS26006 | B3: Abhijeet Vijaysingh Pardeshi | C3: 46062 | D3: 70833 | E3: 28 | F3: 20 | G3: 0 | I3: =(+D3*49.99999%)/E3*F3 -> 25297.495 | J3: =(I3*50%) -> 12648.747 | K3: =(1600/E3)*F3 -> 1142.8571 | L3: =(M3-I3-J3-K3) -> 9003.3767 | M3: =(D3-X3)/E3*F3-Z3 -> 48092.476 | N3: =IF($I3*0.12>1800,1800,$I3*0.12) -> 1800 | O3: =IF(M3<=21000,M3*0.75%,0) -> 0 | P3: 200 | Q3: 0 | R3: 0 | S3: 0 | T3: =M3+Q3+R3+S3 -> 48092.476 | U3: 0 | V3: 0 | W3: 0 | X3: =IF($I3*0.12>1800,1800,$I3*0.12) -> 1800 | Y3: =IF(M3<=21000,M3*3.25%,0) -> 0 | Z3: =I3*4.81% -> 1216.8095 | AA3: =N3+O3+P3+V3+W3+U3+X3+Y3+Z3 -> 5016.8095 | AB3: =M3-AA3 -> 43075.667
A4: AGS26009 | B4: Sarika Lingarkar | C4: 46064 | D4: 70833 | E4: 28 | F4: 4 | G4: 16 | I4: =(+D4*49.99999%)/E4*F4 -> 5059.499 | J4: =(I4*50%) -> 2529.7495 | K4: =(1600/E4)*F4 -> 228.57143 | L4: =(M4-I4-J4-K4) -> 1800.6753 | M4: =(D4-X4)/E4*F4-Z4 -> 9618.4952 | N4: 1800 | O4: 0 | P4: 200 | Q4: 0 | R4: 0 | S4: 0 | T4: =M4+Q4+R4+S4 -> 9618.4952 | U4: 0 | V4: 0 | W4: 0 | X4: 1800 | Y4: 0 | Z4: =I4*4.81% -> 243.3619 | AA4: =N4+O4+P4+V4+W4+U4+X4+Y4+Z4 -> 4043.3619 | AB4: =M4-AA4 -> 5575.1333
C9: Total | D9: =SUM(D2:D8) -> 258333 | I9: =SUM(I2:I8) -> 63690.416 | J9: =SUM(J2:J8) -> 31845.208 | K9: =SUM(K2:K8) -> 2285.7143 | L9: =SUM(L2:L8) -> 23924.582 | M9: =SUM(M2:M8) -> 121745.92 | N9: =SUM(N2:N8) -> 5400 | O9: =SUM(O2:O8) -> 0 | P9: =SUM(P2:P8) -> 600 | ... AB9: =SUM(AB2:AB8) -> 107282.41

Sheet Consultant
A1: Employee ID | B1: Employee Name | C1: DOJ | D1: CTC | E1: Actuals | F1: TDS | G1: PT | H1: Payable
A2: AGS26004 | B2: Ande Sharath Chandra | C2: 46055 | D2: 80000 | E2: =D2/30*29 -> 77333.333 | F2: 0 | G2: 200 | H2: =E2-G2 -> 77133.333
A3: AGS26005 | B3: Tanakala Janardhan | C3: 46055 | D3: 70000 | E3: =D3/30*29 -> 67666.667 | F3: 0 | G3: 200 | H3: =E3-G3 -> 67466.667
A4: AGS26020 | B4: Gurindapalli Krishna Chaitanya | C4: 46066 | D4: 60000 | E4: =D4/30*18 -> 36000 | F4: 0 | G4: 200 | H4: =E4-G4 -> 35800
A5: AGS26024 | B5: Priya Darshini Pola | C5: 46072 | D5: 80000 | E5: =D5/30*12 -> 32000 | F5: 0 | G5: 200 | H5: =E5-G5 -> 31800
G7: Total | H7: =SUM(H2:H5) -> 212200

Sheet Payment
A1: Employee ID | B1: Employee Name | C1: DOJ | D1: Net Salary Payable | E1: Bank Account Number | F1: IFSC code | G1: Bank Name | H1: Remarks
A2: AGS26006 | B2: Abhijeet Vijaysingh Pardeshi | C2: 46062 | D2: =Employees!AB3 -> 43075.667 | E2: 41280100007853 | F2: BARB0WALUJX | G2: BANK OF BARODA | H2: Process
A3: AGS26004 | B3: Ande Sharath Chandra | C3: 46054 | D3: =Consultant!H2 -> 77133.333 | E3: 50100677371816 | F3: HDFC0001042 | G3: HDFC Bank | H3: Process
A4: AGS26005 | B4: Tanakala Janardhan | C4: 46054 | D4: =Consultant!H3 -> 67466.667 | E4: 154710100018477 | F4: UBIN0815471 | G4: Union Bank | H4: Process
A5: AGS26020 | B5: Gurindapalli Krishna Chaitanya | C5: 46066 | D5: =Consultant!H4 -> 35800 | E5: 020201545829 | F5: ICIC0000202 | G5: ICICI Bank | H5: Process
A6: AGS26024 | B6: Priya Darshini Pola | C6: 46072 | D6: =Consultant!H5 -> 31800 | E6: 770301501355 | F6: ICIC0007703 | G6: ICICI Bank | H6: Process
A7: AGS26009 | B7: Sarika Lingarkar | C7: 46072 | D7: =Employees!AB4 -> 5575.1333 | E7: 000801621546 | F7: ICIC0000008 | G7: ICICI Bank | H7: F&F
B9: Total | D9: =SUM(D2:D7) -> 260850.8
A13: Employee ID | B13: Employee Name | C13: DOJ | D13: Net Salary Payable | E13: Bank Account Number | F13: IFSC code | G13: Bank Name | H13: Remarks
A14: AGS26007 | B14: Mandela Sai Sandeep | C14: 46062 | D14: =Employees!AB2 -> 58631.611 | E14: 44611426067 | F14: SCBL0036075 | G14: Standard Chartered | H14: Hold - F&F
